ipymidi/__init__.py
ipymidi/event.py
ipymidi/event_traits.py
ipymidi/interface.py
ipymidi/static/index.js
ipymidi-0.0.1.dist-info/METADATA
ipymidi-0.0.1.dist-info/WHEEL
ipymidi-0.0.1.dist-info/licenses/LICENSE
ipymidi-0.0.1.dist-info/RECORD
