Metadata-Version: 2.1
Name: ipymidi
Version: 0.0.1
Summary: Interactive MIDI in Jupyter
Project-URL: Repository, https://github.com/benbovy/ipymidi
Author: Benoît Bovy
Maintainer: ipymidi contributors
License: BSD-3-Clause
License-File: LICENSE
Keywords: MIDI,jupyter,widget
Requires-Dist: anywidget
Provides-Extra: dev
Requires-Dist: jupyterlab; extra == 'dev'
Requires-Dist: watchfiles; extra == 'dev'
